fastwoe/__init__.py
fastwoe/display.py
fastwoe/fast_somersd.py
fastwoe/fastwoe.py
fastwoe/fastwoe_multiclass.py
fastwoe/interpret_fastwoe.py
fastwoe/logging_config.py
fastwoe/metrics.py
fastwoe/plots.py
fastwoe/screening.py
fastwoe-0.1.6.dist-info/METADATA
fastwoe-0.1.6.dist-info/WHEEL
fastwoe-0.1.6.dist-info/licenses/LICENSE
fastwoe-0.1.6.dist-info/RECORD
