Metadata-Version: 2.4
Name: fastwoe
Version: 0.1.6
Summary: Fast Weight of Evidence (WOE) encoding and inference
Project-URL: Homepage, https://github.com/xRiskLab/fastwoe
Project-URL: Repository, https://github.com/xRiskLab/fastwoe
Project-URL: Documentation, https://github.com/xRiskLab/fastwoe#readme
Project-URL: Issues, https://github.com/xRiskLab/fastwoe/issues
Project-URL: PyPI, https://pypi.org/project/fastwoe/
Author-email: xRiskLab <contact@xrisklab.ai>
License: MIT
License-File: LICENSE
Keywords: feature-engineering,machine-learning,statistical-inference,weight-of-evidence,woe
Classifier: Development Status :: 4 - Beta
Classifier: Intended Audience :: Developers
Classifier: Intended Audience :: Science/Research
Classifier: License :: OSI Approved :: MIT License
Classifier: Programming Language :: Python :: 3
Classifier: Programming Language :: Python :: 3.9
Classifier: Programming Language :: Python :: 3.10
Classifier: Programming Language :: Python :: 3.11
Classifier: Programming Language :: Python :: 3.12
Classifier: Topic :: Scientific/Engineering :: Artificial Intelligence
Classifier: Topic :: Software Development :: Libraries :: Python Modules
Requires-Python: <3.13,>=3.9
Requires-Dist: loguru>=0.7.0
Requires-Dist: numba>=0.60.0
Requires-Dist: numpy>=1.21.0
Requires-Dist: packaging>=21.0
Requires-Dist: pandas>=1.3.0
Requires-Dist: rich>=13.7.0
Requires-Dist: scikit-learn<1.8.0,>=1.3.0
Requires-Dist: scipy>=1.7.0
Provides-Extra: dev
Requires-Dist: black>=22.0.0; extra == 'dev'
Requires-Dist: pytest-cov>=4.0.0; extra == 'dev'
Requires-Dist: pytest>=7.0.0; extra == 'dev'
Requires-Dist: ruff>=0.11.13; extra == 'dev'
Provides-Extra: examples
Requires-Dist: fisher-scoring>=2.0.5; extra == 'examples'
Requires-Dist: jupyter>=1.0.0; extra == 'examples'
Requires-Dist: matplotlib>=3.5.0; extra == 'examples'
Requires-Dist: pygam>=0.10.1; extra == 'examples'
Requires-Dist: seaborn>=0.11.0; extra == 'examples'
Requires-Dist: statsmodels>=0.13.0; extra == 'examples'
Provides-Extra: faiss
Requires-Dist: faiss-cpu>=1.12.0; extra == 'faiss'
Provides-Extra: faiss-gpu
Requires-Dist: faiss-gpu-cu12>=1.12.0; extra == 'faiss-gpu'
Provides-Extra: plotting
Requires-Dist: matplotlib>=3.5.0; extra == 'plotting'
